pytest_metaexport/__init__.py
pytest_metaexport/decorators.py
pytest_metaexport/figures.py
pytest_metaexport/pytest_metaexport.py
pytest_metaexport/report.py
pytest_metaexport/schema.py
pytest_metaexport/settings.py
pytest_metaexport/utils.py
pytest_metaexport/static/default.html
pytest_metaexport/static/style.css
pytest_metaexport/static/test_entry.html
pytest_metaexport-0.1.3.dist-info/licenses/LICENSE.txt
pytest_metaexport-0.1.3.dist-info/METADATA
pytest_metaexport-0.1.3.dist-info/WHEEL
pytest_metaexport-0.1.3.dist-info/entry_points.txt
pytest_metaexport-0.1.3.dist-info/top_level.txt
pytest_metaexport-0.1.3.dist-info/RECORD
