Metadata-Version: 2.4
Name: pytest-metaexport
Version: 0.1.3
Summary: Pytest plugin for exporting custom test metadata to JSON.
License-Expression: MIT
Project-URL: Homepage, https://github.com/Ecaloota/pytest-metaexport
Project-URL: Repository, https://github.com/Ecaloota/pytest-metaexport
Requires-Python: >=3.12
License-File: LICENSE.txt
Requires-Dist: pytest>=7.1.0
Requires-Dist: pandas>=2.3.0
Requires-Dist: kaleido>=1.0.0
Requires-Dist: Jinja2>=3.1.6
Requires-Dist: weasyprint>=65.1
Requires-Dist: pydantic>=2.11.7
Requires-Dist: pydantic_settings>=2.10.0
Requires-Dist: plotly>=6.1.1
Requires-Dist: kaleido>=1.0.0
Dynamic: license-file
